at30ts00/__init__.py
at30ts00/at30ts00.py
at30ts00-1.0.0.dist-info/LICENSE
at30ts00-1.0.0.dist-info/METADATA
at30ts00-1.0.0.dist-info/WHEEL
at30ts00-1.0.0.dist-info/top_level.txt
at30ts00-1.0.0.dist-info/RECORD
